<?xml version="1.0" encoding="UTF-8"?>
<!DOCTYPE mapper PUBLIC "-//mybatis.org//DTD Mapper 3.0//EN" "http://mybatis.org/dtd/mybatis-3-mapper.dtd">
<mapper namespace="com.waittime.backend.db.gen.client.DimProcedureMapper">
  <resultMap id="BaseResultMap" type="com.waittime.backend.db.gen.model.DimProcedure">
    <!--
      WARNING - @mbg.generated
      This element is automatically generated by MyBatis Generator, do not modify.
      This element was generated on Fri Nov 17 17:54:11 PST 2017.
    -->
    <id column="procedure_id" jdbcType="INTEGER" property="procedure_id" />
    <result column="procedure_name" jdbcType="VARCHAR" property="procedure_name" />
    <result column="expected_duration" jdbcType="INTEGER" property="expected_duration" />
    <result column="average_duration" jdbcType="INTEGER" property="average_duration" />
  </resultMap>
  <sql id="Example_Where_Clause">
    <!--
      WARNING - @mbg.generated
      This element is automatically generated by MyBatis Generator, do not modify.
      This element was generated on Fri Nov 17 17:54:11 PST 2017.
    -->
    <where>
      <foreach collection="oredCriteria" item="criteria" separator="or">
        <if test="criteria.valid">
          <trim prefix="(" prefixOverrides="and" suffix=")">
            <foreach collection="criteria.criteria" item="criterion">
              <choose>
                <when test="criterion.noValue">
                  and ${criterion.condition}
                </when>
                <when test="criterion.singleValue">
                  and ${criterion.condition} #{criterion.value}
                </when>
                <when test="criterion.betweenValue">
                  and ${criterion.condition} #{criterion.value} and #{criterion.secondValue}
                </when>
                <when test="criterion.listValue">
                  and ${criterion.condition}
                  <foreach close=")" collection="criterion.value" item="listItem" open="(" separator=",">
                    #{listItem}
                  </foreach>
                </when>
              </choose>
            </foreach>
          </trim>
        </if>
      </foreach>
    </where>
  </sql>
  <sql id="Update_By_Example_Where_Clause">
    <!--
      WARNING - @mbg.generated
      This element is automatically generated by MyBatis Generator, do not modify.
      This element was generated on Fri Nov 17 17:54:11 PST 2017.
    -->
    <where>
      <foreach collection="example.oredCriteria" item="criteria" separator="or">
        <if test="criteria.valid">
          <trim prefix="(" prefixOverrides="and" suffix=")">
            <foreach collection="criteria.criteria" item="criterion">
              <choose>
                <when test="criterion.noValue">
                  and ${criterion.condition}
                </when>
                <when test="criterion.singleValue">
                  and ${criterion.condition} #{criterion.value}
                </when>
                <when test="criterion.betweenValue">
                  and ${criterion.condition} #{criterion.value} and #{criterion.secondValue}
                </when>
                <when test="criterion.listValue">
                  and ${criterion.condition}
                  <foreach close=")" collection="criterion.value" item="listItem" open="(" separator=",">
                    #{listItem}
                  </foreach>
                </when>
              </choose>
            </foreach>
          </trim>
        </if>
      </foreach>
    </where>
  </sql>
  <sql id="Base_Column_List">
    <!--
      WARNING - @mbg.generated
      This element is automatically generated by MyBatis Generator, do not modify.
      This element was generated on Fri Nov 17 17:54:11 PST 2017.
    -->
    procedure_id, procedure_name, expected_duration, average_duration
  </sql>
  <select id="selectByExample" parameterType="com.waittime.backend.db.gen.model.DimProcedureExample" resultMap="BaseResultMap">
    <!--
      WARNING - @mbg.generated
      This element is automatically generated by MyBatis Generator, do not modify.
      This element was generated on Fri Nov 17 17:54:11 PST 2017.
    -->
    select
    <if test="distinct">
      distinct
    </if>
    <include refid="Base_Column_List" />
    from dim_procedure
    <if test="_parameter != null">
      <include refid="Example_Where_Clause" />
    </if>
    <if test="orderByClause != null">
      order by ${orderByClause}
    </if>
  </select>
  <select id="selectByPrimaryKey" parameterType="java.lang.Integer" resultMap="BaseResultMap">
    <!--
      WARNING - @mbg.generated
      This element is automatically generated by MyBatis Generator, do not modify.
      This element was generated on Fri Nov 17 17:54:11 PST 2017.
    -->
    select 
    <include refid="Base_Column_List" />
    from dim_procedure
    where procedure_id = #{procedure_id,jdbcType=INTEGER}
  </select>
  <delete id="deleteByPrimaryKey" parameterType="java.lang.Integer">
    <!--
      WARNING - @mbg.generated
      This element is automatically generated by MyBatis Generator, do not modify.
      This element was generated on Fri Nov 17 17:54:11 PST 2017.
    -->
    delete from dim_procedure
    where procedure_id = #{procedure_id,jdbcType=INTEGER}
  </delete>
  <delete id="deleteByExample" parameterType="com.waittime.backend.db.gen.model.DimProcedureExample">
    <!--
      WARNING - @mbg.generated
      This element is automatically generated by MyBatis Generator, do not modify.
      This element was generated on Fri Nov 17 17:54:11 PST 2017.
    -->
    delete from dim_procedure
    <if test="_parameter != null">
      <include refid="Example_Where_Clause" />
    </if>
  </delete>
  <insert id="insert" parameterType="com.waittime.backend.db.gen.model.DimProcedure">
    <!--
      WARNING - @mbg.generated
      This element is automatically generated by MyBatis Generator, do not modify.
      This element was generated on Fri Nov 17 17:54:11 PST 2017.
    -->
    insert into dim_procedure (procedure_id, procedure_name, expected_duration, 
      average_duration)
    values (#{procedure_id,jdbcType=INTEGER}, #{procedure_name,jdbcType=VARCHAR}, #{expected_duration,jdbcType=INTEGER}, 
      #{average_duration,jdbcType=INTEGER})
  </insert>
  <insert id="insertSelective" parameterType="com.waittime.backend.db.gen.model.DimProcedure">
    <!--
      WARNING - @mbg.generated
      This element is automatically generated by MyBatis Generator, do not modify.
      This element was generated on Fri Nov 17 17:54:11 PST 2017.
    -->
    insert into dim_procedure
    <trim prefix="(" suffix=")" suffixOverrides=",">
      <if test="procedure_id != null">
        procedure_id,
      </if>
      <if test="procedure_name != null">
        procedure_name,
      </if>
      <if test="expected_duration != null">
        expected_duration,
      </if>
      <if test="average_duration != null">
        average_duration,
      </if>
    </trim>
    <trim prefix="values (" suffix=")" suffixOverrides=",">
      <if test="procedure_id != null">
        #{procedure_id,jdbcType=INTEGER},
      </if>
      <if test="procedure_name != null">
        #{procedure_name,jdbcType=VARCHAR},
      </if>
      <if test="expected_duration != null">
        #{expected_duration,jdbcType=INTEGER},
      </if>
      <if test="average_duration != null">
        #{average_duration,jdbcType=INTEGER},
      </if>
    </trim>
  </insert>
  <select id="countByExample" parameterType="com.waittime.backend.db.gen.model.DimProcedureExample" resultType="java.lang.Long">
    <!--
      WARNING - @mbg.generated
      This element is automatically generated by MyBatis Generator, do not modify.
      This element was generated on Fri Nov 17 17:54:11 PST 2017.
    -->
    select count(*) from dim_procedure
    <if test="_parameter != null">
      <include refid="Example_Where_Clause" />
    </if>
  </select>
  <update id="updateByExampleSelective" parameterType="map">
    <!--
      WARNING - @mbg.generated
      This element is automatically generated by MyBatis Generator, do not modify.
      This element was generated on Fri Nov 17 17:54:11 PST 2017.
    -->
    update dim_procedure
    <set>
      <if test="record.procedure_id != null">
        procedure_id = #{record.procedure_id,jdbcType=INTEGER},
      </if>
      <if test="record.procedure_name != null">
        procedure_name = #{record.procedure_name,jdbcType=VARCHAR},
      </if>
      <if test="record.expected_duration != null">
        expected_duration = #{record.expected_duration,jdbcType=INTEGER},
      </if>
      <if test="record.average_duration != null">
        average_duration = #{record.average_duration,jdbcType=INTEGER},
      </if>
    </set>
    <if test="_parameter != null">
      <include refid="Update_By_Example_Where_Clause" />
    </if>
  </update>
  <update id="updateByExample" parameterType="map">
    <!--
      WARNING - @mbg.generated
      This element is automatically generated by MyBatis Generator, do not modify.
      This element was generated on Fri Nov 17 17:54:11 PST 2017.
    -->
    update dim_procedure
    set procedure_id = #{record.procedure_id,jdbcType=INTEGER},
      procedure_name = #{record.procedure_name,jdbcType=VARCHAR},
      expected_duration = #{record.expected_duration,jdbcType=INTEGER},
      average_duration = #{record.average_duration,jdbcType=INTEGER}
    <if test="_parameter != null">
      <include refid="Update_By_Example_Where_Clause" />
    </if>
  </update>
  <update id="updateByPrimaryKeySelective" parameterType="com.waittime.backend.db.gen.model.DimProcedure">
    <!--
      WARNING - @mbg.generated
      This element is automatically generated by MyBatis Generator, do not modify.
      This element was generated on Fri Nov 17 17:54:11 PST 2017.
    -->
    update dim_procedure
    <set>
      <if test="procedure_name != null">
        procedure_name = #{procedure_name,jdbcType=VARCHAR},
      </if>
      <if test="expected_duration != null">
        expected_duration = #{expected_duration,jdbcType=INTEGER},
      </if>
      <if test="average_duration != null">
        average_duration = #{average_duration,jdbcType=INTEGER},
      </if>
    </set>
    where procedure_id = #{procedure_id,jdbcType=INTEGER}
  </update>
  <update id="updateByPrimaryKey" parameterType="com.waittime.backend.db.gen.model.DimProcedure">
    <!--
      WARNING - @mbg.generated
      This element is automatically generated by MyBatis Generator, do not modify.
      This element was generated on Fri Nov 17 17:54:11 PST 2017.
    -->
    update dim_procedure
    set procedure_name = #{procedure_name,jdbcType=VARCHAR},
      expected_duration = #{expected_duration,jdbcType=INTEGER},
      average_duration = #{average_duration,jdbcType=INTEGER}
    where procedure_id = #{procedure_id,jdbcType=INTEGER}
  </update>
</mapper>